jupyter_voicepilot/__init__.py
jupyter_voicepilot/_version.py
jupyter_voicepilot-0.1.2.data/data/share/jupyter/labextensions/voicepilot/package.json
jupyter_voicepilot-0.1.2.data/data/share/jupyter/labextensions/voicepilot/schemas/voicepilot/package.json.orig
jupyter_voicepilot-0.1.2.data/data/share/jupyter/labextensions/voicepilot/schemas/voicepilot/plugin.json
jupyter_voicepilot-0.1.2.data/data/share/jupyter/labextensions/voicepilot/static/484.89ad9e9e0e2c63db0a8c.js
jupyter_voicepilot-0.1.2.data/data/share/jupyter/labextensions/voicepilot/static/485.e650a21cfb90e6407c5c.js
jupyter_voicepilot-0.1.2.data/data/share/jupyter/labextensions/voicepilot/static/496.f4837d51166d7104dd2f.js
jupyter_voicepilot-0.1.2.data/data/share/jupyter/labextensions/voicepilot/static/747.5f1ebb2e2b503421e9d6.js
jupyter_voicepilot-0.1.2.data/data/share/jupyter/labextensions/voicepilot/static/remoteEntry.8801bf73507f23e3b027.js
jupyter_voicepilot-0.1.2.data/data/share/jupyter/labextensions/voicepilot/static/style.js
jupyter_voicepilot-0.1.2.data/data/share/jupyter/labextensions/voicepilot/static/third-party-licenses.json
jupyter_voicepilot-0.1.2.data/data/share/jupyter/labextensions/voicepilot/install.json
jupyter_voicepilot-0.1.2.dist-info/METADATA
jupyter_voicepilot-0.1.2.dist-info/WHEEL
jupyter_voicepilot-0.1.2.dist-info/licenses/LICENSE
jupyter_voicepilot-0.1.2.dist-info/RECORD
