Metadata-Version: 2.1
Name: jupyter_voicepilot
Version: 0.1.2
Summary: A JupyterLab extension for generating code and interacting with JupyterLab via voice commands.
Project-URL: Homepage, https://github.com/JovanVeljanoski/jupyter-voicepilot
Project-URL: Bug Tracker, https://github.com/JovanVeljanoski/jupyter-voicepilot/issues
Project-URL: Repository, https://github.com/JovanVeljanoski/jupyter-voicepilot.git
Author-email: Jovan Veljanoski <jovan.veljanoski@gmail.com>
License: MIT License
License-File: LICENSE
Classifier: Framework :: Jupyter
Classifier: Framework :: Jupyter :: JupyterLab
Classifier: Framework :: Jupyter :: JupyterLab :: 3
Classifier: Framework :: Jupyter :: JupyterLab :: Extensions
Classifier: Framework :: Jupyter :: JupyterLab :: Extensions :: Prebuilt
Classifier: License :: OSI Approved :: BSD License
Classifier: Programming Language :: Python
Classifier: Programming Language :: Python :: 3
Classifier: Programming Language :: Python :: 3.7
Classifier: Programming Language :: Python :: 3.8
Classifier: Programming Language :: Python :: 3.9
Classifier: Programming Language :: Python :: 3.10
Classifier: Programming Language :: Python :: 3.11
Requires-Python: >=3.7
